{
  "output": {
    "SCF": {
      "nucl_rep_energy": 12.96484260525531,
      "iter": {
        "1": {
          "energy": -108.35786097172739,
          "e_diff": -108.35786097172739,
          "rmsd": 0.0010690184712924017,
          "performance": {
            "total_time": 0.416554476
          }
        },
        "2": {
          "energy": -108.36462536290064,
          "e_diff": -0.006764391173248896,
          "rmsd": 0.00033371111493539724,
          "performance": {
            "total_time": 0.418606636
          }
        },
        "3": {
          "energy": -108.36552605451301,
          "e_diff": -0.000900691612372384,
          "rmsd": 0.00018546266235316015,
          "performance": {
            "total_time": 0.41869325
          }
        },
        "4": {
          "energy": -108.3656839017387,
          "e_diff": -0.00015784722569378573,
          "rmsd": 1.2000047149562131e-05,
          "performance": {
            "total_time": 0.425153686
          }
        },
        "5": {
          "energy": -108.36568451651114,
          "e_diff": -6.147724320726411e-07,
          "rmsd": 2.044347325258965e-06,
          "performance": {
            "total_time": 0.419867418
          }
        },
        "6": {
          "energy": -108.3656845336965,
          "e_diff": -1.7185357137350366e-08,
          "rmsd": 4.6743749003239775e-07,
          "performance": {
            "total_time": 0.421341392
          }
        },
        "7": {
          "energy": -108.36568453417566,
          "e_diff": -4.791615992871812e-10,
          "rmsd": 1.343546589823182e-07,
          "performance": {
            "total_time": 0.424446444
          }
        },
        "8": {
          "energy": -108.36568453419682,
          "e_diff": -2.1159962670935784e-11,
          "rmsd": 1.060661487876393e-08,
          "performance": {
            "total_time": 0.426795973
          }
        },
        "9": {
          "energy": -108.36568453419689,
          "e_diff": -7.105427357601002e-14,
          "rmsd": 7.800982492701e-10,
          "performance": {
            "total_time": 0.427619225
          }
        }
      },
      "final_energy": -108.36568453419689,
      "n_iterations": 9
    },
    "CD": {
      "n_cholesky_vectors": 796
    },
    "CCSD": {
      "iter": {
        "1": {
          "residual": 1.029561425722476,
          "correlation": 0.0,
          "performance": {
            "total_time": 3.282415197
          }
        },
        "2": {
          "residual": 0.3806227599594906,
          "correlation": -0.9583077178250564,
          "performance": {
            "total_time": 3.033767014
          }
        },
        "3": {
          "residual": 0.5637137906590426,
          "correlation": -0.16192036200478635,
          "performance": {
            "total_time": 3.051641879
          }
        },
        "4": {
          "residual": 0.7307624764008961,
          "correlation": -1.3297893506349645,
          "performance": {
            "total_time": 3.037312773
          }
        },
        "5": {
          "residual": 1.0468641686499585,
          "correlation": 0.19520402025528893,
          "performance": {
            "total_time": 3.036128175
          }
        },
        "6": {
          "residual": 0.04610929168117611,
          "correlation": -0.6682965725506347,
          "performance": {
            "total_time": 3.033598655
          }
        },
        "7": {
          "residual": 0.06841193383100191,
          "correlation": -0.5864772015423592,
          "performance": {
            "total_time": 3.043807687
          }
        },
        "8": {
          "residual": 0.07965203078912593,
          "correlation": -0.7155416244177492,
          "performance": {
            "total_time": 3.023532655
          }
        },
        "9": {
          "residual": 0.12305075658101135,
          "correlation": -0.5479466142399501,
          "performance": {
            "total_time": 3.020412769
          }
        },
        "10": {
          "residual": 0.1613364338750014,
          "correlation": -0.7926065927196624,
          "performance": {
            "total_time": 3.022378863
          }
        },
        "11": {
          "residual": 0.006002276552785386,
          "correlation": -0.6616131018174614,
          "performance": {
            "total_time": 3.048668866
          }
        },
        "12": {
          "residual": 0.00811057964296122,
          "correlation": -0.6556606804862786,
          "performance": {
            "total_time": 3.019026789
          }
        },
        "13": {
          "residual": 0.00644901719974461,
          "correlation": -0.6673320846991562,
          "performance": {
            "total_time": 3.019233687
          }
        },
        "14": {
          "residual": 0.011407494821723072,
          "correlation": -0.6543610624300428,
          "performance": {
            "total_time": 3.019897379
          }
        },
        "15": {
          "residual": 0.01279949934358473,
          "correlation": -0.6749463194622978,
          "performance": {
            "total_time": 3.018472997
          }
        },
        "16": {
          "residual": 0.0006479056849236052,
          "correlation": -0.667459127029623,
          "performance": {
            "total_time": 3.033984769
          }
        },
        "17": {
          "residual": 0.00034840163866471234,
          "correlation": -0.6675608229660591,
          "performance": {
            "total_time": 3.020425464
          }
        },
        "18": {
          "residual": 0.00019888863130732327,
          "correlation": -0.6676968244073329,
          "performance": {
            "total_time": 3.020502861
          }
        },
        "19": {
          "residual": 0.0001483485966419569,
          "correlation": -0.667714578485774,
          "performance": {
            "total_time": 3.018226525
          }
        },
        "20": {
          "residual": 8.893100829547504e-05,
          "correlation": -0.6678162042775442,
          "performance": {
            "total_time": 3.014576912
          }
        },
        "21": {
          "residual": 4.897724087587505e-05,
          "correlation": -0.667875697584757,
          "performance": {
            "total_time": 3.022365825
          }
        },
        "22": {
          "residual": 6.56345293483912e-05,
          "correlation": -0.66783358868226,
          "performance": {
            "total_time": 3.013343484
          }
        },
        "23": {
          "residual": 4.9693079670010986e-05,
          "correlation": -0.6679231714539826,
          "performance": {
            "total_time": 3.03650339
          }
        },
        "24": {
          "residual": 9.008794427474416e-05,
          "correlation": -0.6678243388948064,
          "performance": {
            "total_time": 3.017338126
          }
        },
        "25": {
          "residual": 9.849529591438967e-05,
          "correlation": -0.6679838703637722,
          "performance": {
            "total_time": 3.012196556
          }
        },
        "26": {
          "residual": 5.791229790165868e-06,
          "correlation": -0.6679306106953455,
          "performance": {
            "total_time": 2.998455243
          }
        },
        "27": {
          "residual": 2.774620745817989e-06,
          "correlation": -0.6679305867934286,
          "performance": {
            "total_time": 2.987593085
          }
        },
        "28": {
          "residual": 1.428845961402792e-06,
          "correlation": -0.6679320694697514,
          "performance": {
            "total_time": 2.989827401
          }
        },
        "29": {
          "residual": 1.3486872177343833e-06,
          "correlation": -0.6679313566976914,
          "performance": {
            "total_time": 3.00862709
          }
        },
        "30": {
          "residual": 1.0153540850574124e-06,
          "correlation": -0.6679331262294504,
          "performance": {
            "total_time": 2.992319789
          }
        },
        "31": {
          "residual": 3.474545848088492e-07,
          "correlation": -0.6679327125499606,
          "performance": {
            "total_time": 2.995359435
          }
        },
        "32": {
          "residual": 4.4017699149416824e-07,
          "correlation": -0.6679324769168392,
          "performance": {
            "total_time": 2.991524976
          }
        },
        "33": {
          "residual": 3.078334663008347e-07,
          "correlation": -0.6679330257463905,
          "performance": {
            "total_time": 2.985631353
          }
        },
        "34": {
          "residual": 5.539830557148702e-07,
          "correlation": -0.6679324638603107,
          "performance": {
            "total_time": 2.985184913
          }
        },
        "35": {
          "residual": 5.682790899430191e-07,
          "correlation": -0.6679334095827743,
          "performance": {
            "total_time": 2.982289217
          }
        },
        "36": {
          "residual": 4.2156033502968704e-08,
          "correlation": -0.6679331546640647,
          "performance": {
            "total_time": 3.002360964
          }
        },
        "37": {
          "residual": 2.8547142312969836e-08,
          "correlation": -0.6679331391271321,
          "performance": {
            "total_time": 2.986584055
          }
        },
        "38": {
          "residual": 2.256624242634181e-08,
          "correlation": -0.6679331766617211,
          "performance": {
            "total_time": 2.975981278
          }
        },
        "39": {
          "residual": 4.043928808349262e-08,
          "correlation": -0.6679331362453557,
          "performance": {
            "total_time": 2.987180411
          }
        },
        "40": {
          "residual": 6.017405005296484e-08,
          "correlation": -0.6679332009746194,
          "performance": {
            "total_time": 2.987050466
          }
        },
        "41": {
          "residual": 5.209056839004573e-09,
          "correlation": -0.6679331695879983,
          "performance": {
            "total_time": 2.990796167
          }
        }
      },
      "n_iterations": 41,
      "final_energy": {
        "correlation": -0.6679331695879983,
        "total": -109.03361770378488
      }
    }
  },
  "input": {
    "molecule": {
      "name": "N2_2.0",
      "basisset": "cc-pvqz",
      "geometry_units": "angstrom"
    },
    "SCF": {
      "tol_int": 1e-22,
      "tol_sch": 1e-10,
      "tol_lindep": 1e-05,
      "conve": 1e-09,
      "convd": 1e-08,
      "diis_hist": 10,
      "AO_tilesize": 30,
      "force_tilesize": "false",
      "scf_type": "restricted",
      "multiplicity": 1,
      "lambdas": [],
      "polvecs": [],
      "omegas": [],
      "volumes": []
    },
    "CD": {
      "diagtol": 1e-06,
      "itilesize": 1000,
      "write_cv": false,
      "write_vcount": 5000,
      "max_cvecs_factor": 12
    },
    "CCSD": {
      "threshold": 1e-08,
      "tilesize": 40,
      "ndiis": 5,
      "readt": "false",
      "writet": "false",
      "ccsd_maxiter": 50,
      "balance_tiles": "true"
    }
  }
}
